paddleclas/LICENSE
paddleclas/MANIFEST.in
paddleclas/README.md
paddleclas/__init__.py
paddleclas/hubconf.py
paddleclas/paddleclas.py
paddleclas/pyproject.toml
paddleclas/requirements.txt
paddleclas/setup.cfg
paddleclas/setup.py
paddleclas/version.txt
paddleclas/deploy/configs/inference_attr.yaml
paddleclas/deploy/configs/inference_cartoon.yaml
paddleclas/deploy/configs/inference_cls.yaml
paddleclas/deploy/configs/inference_cls_based_action.yaml
paddleclas/deploy/configs/inference_cls_ch4.yaml
paddleclas/deploy/configs/inference_cls_multilabel.yaml
paddleclas/deploy/configs/inference_det.yaml
paddleclas/deploy/configs/inference_drink.yaml
paddleclas/deploy/configs/inference_general.yaml
paddleclas/deploy/configs/inference_general_binary.yaml
paddleclas/deploy/configs/inference_logo.yaml
paddleclas/deploy/configs/inference_product.yaml
paddleclas/deploy/configs/inference_rec.yaml
paddleclas/deploy/configs/inference_vehicle.yaml
paddleclas/deploy/configs/PULC/car_exists/inference_car_exists.yaml
paddleclas/deploy/configs/PULC/language_classification/inference_language_classification.yaml
paddleclas/deploy/configs/PULC/person_attribute/inference_person_attribute.yaml
paddleclas/deploy/configs/PULC/person_exists/inference_person_exists.yaml
paddleclas/deploy/configs/PULC/safety_helmet/inference_safety_helmet.yaml
paddleclas/deploy/configs/PULC/text_image_orientation/inference_text_image_orientation.yaml
paddleclas/deploy/configs/PULC/textline_orientation/inference_textline_orientation.yaml
paddleclas/deploy/configs/PULC/traffic_sign/inference_traffic_sign.yaml
paddleclas/deploy/configs/PULC/vehicle_attribute/inference_vehicle_attribute.yaml
paddleclas/deploy/python/__init__.py
paddleclas/deploy/python/build_gallery.py
paddleclas/deploy/python/det_preprocess.py
paddleclas/deploy/python/postprocess.py
paddleclas/deploy/python/predict_cls.py
paddleclas/deploy/python/predict_det.py
paddleclas/deploy/python/predict_rec.py
paddleclas/deploy/python/predict_system.py
paddleclas/paddleclas.egg-info/PKG-INFO
paddleclas/paddleclas.egg-info/SOURCES.txt
paddleclas/paddleclas.egg-info/dependency_links.txt
paddleclas/paddleclas.egg-info/entry_points.txt
paddleclas/paddleclas.egg-info/requires.txt
paddleclas/paddleclas.egg-info/top_level.txt
paddleclas-2.5.2.dist-info/LICENSE
paddleclas-2.5.2.dist-info/METADATA
paddleclas-2.5.2.dist-info/WHEEL
paddleclas-2.5.2.dist-info/entry_points.txt
paddleclas-2.5.2.dist-info/top_level.txt
paddleclas-2.5.2.dist-info/RECORD
