Metadata-Version: 2.1
Name: paddleclas
Version: 2.5.2
Summary: A treasure chest for visual recognition powered by PaddlePaddle.
Home-page: https://github.com/PaddlePaddle/PaddleClas
Download-URL: https://github.com/PaddlePaddle/PaddleClas.git
License: Apache License
Keywords: image-classification,image-recognition,pretrained-models,knowledge-distillation,product-recognition,autoaugment,cutmix,randaugment,gridmask,deit,repvgg,swin-transformer,image-retrieval-system
Classifier: Development Status :: 5 - Production/Stable
Classifier: Operating System :: OS Independent
Classifier: Intended Audience :: Developers
Classifier: Intended Audience :: Education
Classifier: Intended Audience :: Science/Research
Classifier: License :: OSI Approved :: Apache Software License
Requires-Python: >=3.8
License-File: LICENSE
Requires-Dist: prettytable
Requires-Dist: ujson
Requires-Dist: opencv-python ==4.6.0.66
Requires-Dist: pillow
Requires-Dist: tqdm
Requires-Dist: PyYAML >=5.1
Requires-Dist: visualdl >=2.2.0
Requires-Dist: scipy >=1.0.0
Requires-Dist: scikit-learn >=0.21.0
Requires-Dist: gast ==0.3.3
Requires-Dist: faiss-cpu
Requires-Dist: easydict
